{
    "model": "meta-llama/Llama-2-7b-hf",
    "heads": [
        {
            "layer": 16,
            "head": 19,
            "score": 0.18179966509342194
        },
        {
            "layer": 16,
            "head": 24,
            "score": 0.10288331657648087
        },
        {
            "layer": 21,
            "head": 1,
            "score": 0.08611086010932922
        },
        {
            "layer": 18,
            "head": 30,
            "score": 0.07593841850757599
        },
        {
            "layer": 20,
            "head": 5,
            "score": 0.06847432255744934
        },
        {
            "layer": 17,
            "head": 22,
            "score": 0.06669752299785614
        },
        {
            "layer": 31,
            "head": 27,
            "score": 0.06533610075712204
        },
        {
            "layer": 17,
            "head": 11,
            "score": 0.06090545654296875
        },
        {
            "layer": 29,
            "head": 19,
            "score": 0.05579020455479622
        },
        {
            "layer": 14,
            "head": 18,
            "score": 0.05550367757678032
        },
        {
            "layer": 15,
            "head": 22,
            "score": 0.04506348446011543
        },
        {
            "layer": 20,
            "head": 12,
            "score": 0.04421624168753624
        },
        {
            "layer": 19,
            "head": 14,
            "score": 0.04035457968711853
        },
        {
            "layer": 21,
            "head": 16,
            "score": 0.03424534201622009
        },
        {
            "layer": 17,
            "head": 30,
            "score": 0.0335320383310318
        },
        {
            "layer": 23,
            "head": 20,
            "score": 0.0271742083132267
        },
        {
            "layer": 19,
            "head": 4,
            "score": 0.0265655517578125
        },
        {
            "layer": 9,
            "head": 25,
            "score": 0.02541622705757618
        },
        {
            "layer": 16,
            "head": 5,
            "score": 0.024561310186982155
        },
        {
            "layer": 31,
            "head": 16,
            "score": 0.02350548654794693
        }
    ]
}